{"nodes": [{"id": "c_users_rafet_documents_spotme_app_jsx", "label": "App.jsx", "file_type": "code", "source_file": "C:\\Users\\Rafet\\Documents\\spotme\\App.jsx", "source_location": "L1"}, {"id": "app_app", "label": "App()", "file_type": "code", "source_file": "C:\\Users\\Rafet\\Documents\\spotme\\App.jsx", "source_location": "L18"}], "edges": [{"source": "c_users_rafet_documents_spotme_app_jsx", "target": "app_app", "relation": "contains", "confidence": "EXTRACTED", "source_file": "C:\\Users\\Rafet\\Documents\\spotme\\App.jsx", "source_location": "L18", "weight": 1.0}], "raw_calls": [{"caller_nid": "app_app", "callee": "useState", "source_file": "C:\\Users\\Rafet\\Documents\\spotme\\App.jsx", "source_location": "L19"}, {"caller_nid": "app_app", "callee": "useState", "source_file": "C:\\Users\\Rafet\\Documents\\spotme\\App.jsx", "source_location": "L20"}, {"caller_nid": "app_app", "callee": "useState", "source_file": "C:\\Users\\Rafet\\Documents\\spotme\\App.jsx", "source_location": "L21"}, {"caller_nid": "app_app", "callee": "useEffect", "source_file": "C:\\Users\\Rafet\\Documents\\spotme\\App.jsx", "source_location": "L24"}, {"caller_nid": "app_app", "callee": "useCallback", "source_file": "C:\\Users\\Rafet\\Documents\\spotme\\App.jsx", "source_location": "L58"}, {"caller_nid": "app_app", "callee": "useCallback", "source_file": "C:\\Users\\Rafet\\Documents\\spotme\\App.jsx", "source_location": "L63"}, {"caller_nid": "app_app", "callee": "useCallback", "source_file": "C:\\Users\\Rafet\\Documents\\spotme\\App.jsx", "source_location": "L68"}]}